{
    "_id": 1870,
    "_header": "He that is all-wielding hath taken a little inn",
    "Subjects": "Christ, Incarnation of; sermons, verse in",
    "Versification": "\u2014 three-line \u2014 aaa",
    "_description": "Miracles of the Incarnation \u2014 three long lines (aaa)",
    "_witnesses": {
        "StPauls9Dxix": {
            "Transcription": "\nHe \u00feat is all weldyng ha\u00fe takyn a lytul In\u00deo kyng of\n                    paradys is komen of sempul kynA mayde kepyng here maydynhod a chyld today\n                    ha\u00fe boryn\n",
            "Note": "\nWritten as prose, lines 3-5.",
            "Editions": "\nWenzel,  Siegfried. \n             \u201cUnrecorded Middle-English Verses.\u201d \n             Anglia\n         92 (1974): 55-78: 62.\n",
            "folio": "f. 70"
        }
    }
}