{
    "_id": 2039,
    "_header": "Holly beareth berries red enough",
    "Subjects": "carols, holy and ivy",
    "Versification": "\u2014 four-line, two-line \u2014 aaaa, aa",
    "_description": "Holly against Ivy \u2014 four monorhyming quatrains and burden: \u2018Nay nay ive it may not be iwis / For holy must haue the mastry as the maner is\u2019",
    "_witnesses": {
        "OxfBal354": {
            "First Lines": "\nHoly berith beris beris rede ynowgh\u00dee tyrtyll\n                    thristilcok \u00fee popyngay dance in euery bowgh\u2026\n",
            "Last Lines": "\n\u2026With a payre of kybid helis cawght with coldSo wold I\n                    \u00feat euery man had \u00feat with yvy will holdExplicit\n",
            "Facsimiles": "\n\nEarly Manuscripts at Oxford University: Facsimile\n                    of Oxford, Balliol MS 354.\n         (http://image.ox.ac.uk/show?collection=balliol&manuscript=ms354). \n",
            "Editions": "\n\nFl\u00fcgel,  Ewald. \n             \u201cEnglische Weihnachtslieder aus einter Handschrift des Balliol College\n                zu Oxford.\u201d \n             Forschungen zur deutschen Philologie. Festgabe f\u00fcr Rudolf\n                Hildebrands.\n         Leipzig: Deit, 1894: 52-84: 83.\nFl\u00fcgel,  Ewald. \n             \u201cLiedersammlungen des XVI Jahrhunderts\u2026.\u201d \n             Anglia\n         26 (1903): 94-285: 279-80.\nDyboski,  R.,\n                        ed.  \n             Songs, Carols and Other Miscellaneous Poems from Balliol MS. 354,\n                Richard Hill\u2019s Commonplace Book.\nEETS\n          e.s. 101 (1908); repr. 1984: 189-90.\nRickert,  Edith,\n                        ed.  \n             Ancient English Christmas Carols.\n         London: Chatto & Windus, 1910: 264-6.\nChambers,  Edmund Kerchever,  and  Frank Sidgwick.  \n             Early English Lyrics\u2026.\n         London: Buller, 1907, 1911 et seq: 239-40.\nGreene,  Richard Leighton. \n             The Early English Carols.\n         Oxford: Clarendon, 1935; 2nd ed., rev., Oxford: Clarendon,\n            1977: 93-4; 1977, 82-3.\nMason,  Harold Andrew. \n             Humanism and Poetry in the Early Tudor Period.\n         London: Routledge and Paul, 1959: 154.\nGreene,  Richard Leighton,\n                        ed.  \n             A Selection of English Carols.\nClarendon Medieval and Tudor Series.\n         Oxford: Clarendon, 1962: 93, 92.\nDavies,  Reginald Thorne. \n             Medieval English Lyrics: a critical anthology.\n         London, 1963; Evanston, IL: Northwestern UP, 1964: 280.\nSpeirs,  John. \n             Medieval English Poetry: the non-Chaucerian Tradition.\n         London: Faber, 1957: 85-6.\n\n",
            "folio": "pp. 5092-510"
        },
        "BLHar5396": {
            "First Lines": "\nHoly stond in the hall fayre to beholdIuy stond without the dore\n                    she ys ful sore a cold\u2026\n",
            "Last Lines": "\n\u2026Gode iuy what byrdys ast thouNon but the howlat that kreye\n                    how how\n",
            "Note": "\n\u201cnay Iuy may hyt shal not be Iwys / Let holy hafe \u00fee maystry as \u00fee maner ys\u201d written above first line; in this witness, couplets followed by one line of the burden written in abbreviated form to right.",
            "Attributed Title": "\nA Song on the Ivy & the Holly  (added above by a later hand, f. 275v)",
            "Editions": "\n\nRitson,  Joseph,\n                        ed.  \n             Ancient Songs from the Time of King Henry the Third to the\n                Revolution.\n         London, 1790. Further editions as Ritson,\n                    Joseph, ed.  Ancient Songs and Ballads\n                from the Reign of King Henry the Second to the Revolution. 2 vols. London,\n            1829; re-ed. \n                William Carew\n                Hazlitt\n             London, 1877: 74; 1829, 1.132-3; 1877,114.\nSandys,  William,\n                        ed.  \n             Christmas Carols, Ancient and Modern.\n         London: Richard Beckley, 1833: 1.\nBrand,  John. \n             Observations on the Popular Antiquities of Great Britain.\n         London: G. Bell, 1849; rev. ed., \n                Sir\n                Henry\n                Ellis\n             3 vols. London: Bohn, 1849. \nHotten,  John Camden,\n                                (alias Joshua Sylvester). \n             A Garland of Christmas Carols, Ancient and Modern.\n         London, 1861 [listed as  \u201cSylvester\u201d  in\n            IMEV]: 144.\nBullen,  Arthur Henry. \n             Carols and Poems from the fifteenth century to the present\n                time.\n         London, 1866, repr. as  Songs and Carols.\n            London: John C. Nimmo, 1885\n            \n                \n                \n            \n        London: John C. Nimmo, 1885: 68.\nHusk,  William Henry. \n             Songs of the Nativity.\n         London, 1867: 131.\nHotten,  John Camden,\n                                (alias Joshua Sylvester). \n             Christmas Carols and Ballads.\n         London, 1874 [listed as  \u201cSylvester\u201d  in\n            IMEV]: 160.\nArber,  Edward. \n             The Dunbar Anthology, 1401-1508.\n         London, New York: Frowde, 1901: 145.\nDyboski,  R.,\n                        ed.  \n             Songs, Carols and Other Miscellaneous Poems from Balliol MS. 354,\n                Richard Hill\u2019s Commonplace Book.\nEETS\n          e.s. 101 (1908); repr. 1984: 116.\nRickert,  Edith,\n                        ed.  \n             Ancient English Christmas Carols.\n         London: Chatto & Windus, 1910: 93, 92.\nDavies,  Reginald Thorne. \n             Medieval English Lyrics: a critical anthology.\n         London, 1963; Evanston, IL: Northwestern UP, 1964: 175.\nSisam,  Celia,  and  Kenneth Sisam, eds.  \n             The Oxford Book of Medieval English Verse.\n         Oxford: Clarendon, 1970: 451.\n\n",
            "folio": "f. 275v"
        }
    }
}