{
    "_id": 2171,
    "_header": "I have a mantle I-maked of cloth",
    "Subjects": "songs; fragments",
    "_description": "A single line fragment of an English song",
    "_witnesses": {
        "BodRawD913": {
            "Transcription": "\nIcha\u00fee a mantel i maket of cloth\u2026\n",
            "Editions": "\n\nHeuser,  Wilhelm. \n             \u201cFragmente von Unbekannten Spielmansliedern des 14. Jahrhunderts, aus\n                Ms. Rawl. D.913.\u201d \n             Angli\n         30 (1907): 173-9: 174.\nWilson,  Richard Middlewood. \n             The Lost Literature of Medieval England.\n         London: Methuen, 1952: 179.\n\n",
            "folio": "f. 1, item 1"
        }
    }
}