{
    "_id": 2180,
    "_header": "I have great marvel of a bird",
    "Subjects": "lovers, unfaithful",
    "Versification": "\u2014 eight-line \u2014 ababbcbc",
    "_description": "On an unfaithful mistress \u2014 in 8-line stanzas (ababbcbc) with refrain, \u2018alas \u00feat euer sho was unkynd\u2019",
    "_witnesses": {
        "Lincoln133": {
            "First Lines": "\nI haue grete maruell off a brydThat with my luff ys went a\n                    wayShe byldes hyr in a no\u00feer stedTher ffore I more both nyght\n                    & day\u2026\n",
            "Last Lines": "\n\u2026A las \u00feat euer sho was vnkyndA las qui ys \u00feat bryd\n                    [ ][ ] I went [ ] luff [ ]\n",
            "Note": "\n18 lines, added to the last leaf of the MS by a later hand; ends\n                    imperfectly (torn).",
            "Editions": "\n\nWoolley,  Reginald Maxwell. \n             Catalogue of the Manuscripts of Lincoln Cathedral Chapter\n                Library.\n         London: Milford, 1927: 95-6.\nWilson,  Richard Middlewood. \n             \u201cMore Lost Literature in Old and Middle English.\u201d \n             Leeds Studies in English\n         5 (1936): 1-49: 37.\nWilson,  Richard Middlewood. \n             The Lost Literature of Medieval England.\n         London: Methuen, 1952: 177-8.\nRobbins,  Rossell Hope,\n                        ed.  \n             Secular Lyrics of the XIV and XV Centuries.\n         2nd ed. Oxford: Clarendon, 1955: 147.\nSisam,  Celia,  and  Kenneth Sisam, eds.  \n             The Oxford Book of Medieval English Verse.\n         Oxford: Clarendon, 1970: 488.\n\n",
            "folio": "f. 122v"
        }
    }
}