{
    "_id": 2203,
    "_header": "I Katherine of the court celestial",
    "Title(s)": "\u2018The speche of Saynt Kateryn\u2019",
    "Subjects": "Arthur, prince of Wales; Catherine of Aragon; pageant verses; occasional verse; Katherine of Alexandria, saint",
    "Versification": "\u2014 seven-line \u2014 ababbcc",
    "_description": "\u2018The speche of Saynt Kateryn\u2019 at the pageant celebrating the marriage of Prince Arthur to Princess Catharine \u2014 four stanzas rhyme royal",
    "_witnesses": {
        "BLCottVitAXVI": {
            "First Lines": "\nI kateryne of the Court Celestyallwhere as it Ioy & perdurable blisse\u2026\n",
            "Last Lines": "\n\u2026Polycy to honour will you streite convoyhast you therefore god spede you on your wey\n",
            "folio": "ff. 184v-185"
        }
    }
}