{
    "_id": 2282,
    "_header": "I sing of kings by the days of Arthur",
    "Title(s)": "Sir Lamwell",
    "Subjects": "romances",
    "Versification": "\u2014 two-line \u2014 aa",
    "_description": "Sir Lamwell \u2014 fragments in short couplets",
    "_witnesses": {
        "CULKk530": {
            "First Lines": "\nListine Lordings by the dayis off ArthureWas britan in grett\n                    honoure\u2026\n",
            "Last Lines": "\n\u2026nocht in the forest ther did sieAne rich Pavillione \u00feer\n                    picht sal lieEwrie pom\n",
            "Note": "\n90 lines.",
            "Editions": "\nFurnivall,  Frederick James,\n                        ed.  \n             Captain Cox., His Ballads and Books.\nBallad Society\n         7 (1871); repr. New Shakespeare Society, 1890: xxxi.\n",
            "folio": "Part II, ff. 11ra-11v"
        }
    }
}