{
    "_id": 2720,
    "_header": "It is beginning of the days brightness",
    "Subjects": "sermons, verse in",
    "Versification": "\u2014 three-line \u2014 aaa",
    "_description": "Three characteristics of dawn, which are compared with advent/birth of the Virgin Mary \u2014 three rhyming lines in a sermon",
    "_witnesses": {
        "CULKk424": {
            "Transcription": "\nhyt ys be gynnyng of \u00fee dayes bry\u021dthnessehyt ys lettyng of\n                    \u00fee penys of wykkydnesse& hyt ys lykyng & cause of\n                    gladnesse\n",
            "Editions": "\nWenzel,  Siegfried. \n             Preachers, Poets and the English Lyric.\n         Princeton: Princeton Univ. Press, 1986: 122-3.\n",
            "folio": "f. 244va"
        }
    }
}