{
    "_id": 3410,
    "_header": "Martha was a good woman all so ye heareth tell",
    "Title(s)": "South English Legendary",
    "Subjects": "Martha, saint, life of; Fronton, saint, life of; saints\u2019 lives",
    "Versification": "\u2014 two-line \u2014 aa",
    "_description": "Life of St. Martha and St. Fronton in the South English Legendary",
    "_witnesses": {
        "BodLauMis463": {
            "First Lines": "\nSEinte Martha a god womman was as \u021de here\u00fe of tellShe\n                    fong oure lord in hire hous as it sei\u00fe in \u00fee\n                    gospel\u2026\n",
            "Last Lines": "\n\u2026Nou lord for \u00fee heye loue \u00deat \u00feu kiddest Martha\n                    \u00feerebring vs to heye blisse \u00feat \u00fee angels here soule\n                    bere\n",
            "Note": "\nTwo columns per page, one full-line, the other half-line.",
            "folio": "ff. 77va-78rb"
        },
        "Bod779": {
            "First Lines": "\nMar\u00fea was a good woman s al so \u021de here\u00fe\n                    telle\u021dhe herberuid Ihesu crist as we finde\u00fe in \u00fee\n                    gospelle\u2026\n",
            "Last Lines": "\n\u2026& leue vs here on er\u00fee doon oure sinnus to bete&\n                    we mot to \u00feat ioye come ar we oure lif here lete\n",
            "Attributed Title": "\nSeint martha mary maudeleynus sustir (f. 242v)",
            "folio": "ff. 242v-244v"
        },
        "BodEngPoeta1": {
            "First Lines": "\nSeint Martha gud wommon was as \u021de schule here telleHeo feng vr\n                    lord in hire hous as hit sei\u00fe in \u00fee gospelle\u2026\n",
            "Last Lines": "\n\u2026Lord for \u00fee he\u021de loue \u00feat kuddest Martha\n                    \u00feereBring vs to \u00feat he\u021de blisse \u00feere \u00fein angeles\n                    hire soule bere. AMEN.\n",
            "Facsimiles": "\n\nDoyle,  I. A.,\n                        ed.  \n             The Vernon Manuscript. A Facsimile of Bodleian Library, Oxford, MS Eng.\n                poet.a.1,\n          with an introduction by A. I. Doyle. Cambridge: D. S. Brewer, 1987. \nScase,  Wendy,  and  Nick Kennedy, eds.  \n             A facsimile edition of the Vernon manuscript: Oxford, Bodleian Library, MS. Eng. Poet. A. 1.\n         Oxford: The Bodleian Library, 2011. \n\n",
            "folio": "ff. 69rb-70ra"
        },
        "OxfTri57": {
            "folio": "f. 90"
        },
        "CamCCC145": {
            "First Lines": "\nSein martha god womman was as \u021de hure\u00fe aldai telleHe\n                    aueng oure louerd in hure hous as it sei\u00fe in \u00fee\n                    gospelle\u2026\n",
            "Last Lines": "\n\u2026Nou louerd for \u00fee heie loue \u00feat \u00feou kuddest martha\n                    \u00feereBring us to \u00fee heie blisse \u00feat \u00fein angles hare\n                    soule bere\n",
            "Editions": "\nD\u2019Evelyn,  Charlotte,  and  A. J. Mill, eds.  \n             The South English Legendary: Corpus Christi College Cambridge MS. 145\n                and British Museum MS. Harley 2277, with variants from Bodley MS. Ashmole 43 and\n                British Museum MS. Cotton Julius D.ix.\nEETS\n         o.s. 235 (1959), 236 (1956); repr. 1967: 348.\n",
            "folio": "ff. 130-132v"
        },
        "CamMagPep2344": {
            "First Lines": "\nSeint Martha a goed womman was as \u021de hure\u00fe al day\n                    telle\u021ceo affeng oure lord in hure hous as hit sei\u00fe in \u00fee\n                    gospelle\u2026\n",
            "Last Lines": "\n\u2026Now lord ffor \u00fee heye loue \u00feat \u00feou kuddest Martha\n                    \u00feereBring vs to \u00fee heye blisse \u00feat \u00feine aungeles hure\n                    to bere\n",
            "Attributed Title": "\nSancta Martha (RT)",
            "folio": "pp. 383-385"
        },
        "CamTCC605": {
            "First Lines": "\nSEint martha was a goud womman as \u021de hure\u00fe tellehes a\n                    fenge oure lord in hure hous as hit se\u00fe in \u00fee\n                    godspelle\u2026\n",
            "Last Lines": "\n\u2026Now for \u00fee swete loue \u00feat \u00feu cuddest martha\n                    \u00feerbrynge ous to \u00fee hey Ioie \u00feat \u00feyne angelis hure\n                    bere\n",
            "Attributed Title": "\nMartha (RT)",
            "Facsimiles": "\n\nDigital Facsimile of Trinity College Cambridge MS R.3.25.\n         https://mss-cat.trin.cam.ac.uk/Manuscript/R.3.25. \n",
            "folio": "ff. 77v-79"
        },
        "BLEge1993": {
            "First Lines": "\nSeint Martha god womman was as \u021de schulen here telleHeo aveng vre lord in hire hous as it sei\u00fe in \u00fee gospelle\u2026\n",
            "Last Lines": "\n\u2026Now lord vor \u00fee hei\u021de loue \u00feat \u00feou kuddest martha \u00feereBringe vs to \u00fee hei\u021de blisse \u00feat \u00fein angles here soule to bere\n",
            "folio": "ff. 201v-203v"
        },
        "BLEge2891": {
            "First Lines": "\nSEin Martha god womman was as \u021de hure\u00fe alday telleHeo aneng oure louerd in hure hous as it sei\u00fe In \u00fee gospelle\u2026\n",
            "Last Lines": "\n\u2026Nou louerd for \u00fee heie loue \u00feat \u00feou kuddest martha \u00feereBring us to \u00fee heie blisse \u00feat \u00fein angles hure soule bere\n",
            "folio": "ff. 126-128"
        },
        "BLHar2277": {
            "First Lines": "\nSEinte Martha a god womman was as \u021de hure\u00fe aldai telleHeo afeng oure louerd in hire hous as hit sai\u00fe in \u00fee godspelle\u2026\n",
            "Last Lines": "\n\u2026& bureden hit wi\u00fe here owe hond oure louerd & Seint ffroutonA fairere buringe \u00fean \u00feer was me ne hurde neuere non\u2026\n",
            "Note": "\nEnds incomplete.",
            "Facsimiles": "\n\nDigital Facsimile of British Library Harley MS 2277.\n         https://www.bl.uk/manuscripts/FullDisplay.aspx?index=0&ref=Harley_MS_2277. \n",
            "folio": "ff. 104-105v"
        },
        "BLAdd10301": {
            "First Lines": "\nSEin Martha gode womman was as \u021de hure\u00fe al day\n                    telle\u021do reseyvid oure lorde in hire hous as it sei\u00fe in \u00fee\n                    gospelle\u2026\n",
            "Last Lines": "\n\u2026Nou lord for \u00fee heye love \u00feat \u00feou kuddest Martha\n                    \u00feereBring vs to \u00fee heye blisse \u00feat \u00fein angles hure\n                    soule bere\n",
            "Attributed Title": "\nSancta Martha (f. 149, by scribe in margin beside first line);\n                        Martha (RT)",
            "folio": "ff. 149-152v"
        }
    }
}