{
    "_id": 3836,
    "_header": "O blessed God that art almighty",
    "Subjects": "prayers, of confession; confession",
    "Versification": "\u2014 two-line \u2014 aa",
    "_description": "A prayer of confession \u2014 94 long lines, generally in couplets",
    "_witnesses": {
        "Bod850": {
            "First Lines": "\nBlissed god \u00feat art almi\u021dti\u00feou arte ful of goodnesse\n                    euer full of mercy\u2026\n",
            "Last Lines": "\n\u2026That fully what we hope trustelygraunt vs \u00feat graciously\n                    Ihesu \u00feat art almi\u021dti\n",
            "Note": "\nWritten as prose.",
            "Editions": "\nBrown,  Carleton Fairchild,\n                        ed.  \n             Religious Lyrics of the XVth Century.\n         Oxford: Clarendon, 1939: 217-21.\n",
            "folio": "dd. 87vb-90rb"
        }
    }
}