{
    "_id": 4028,
    "_header": "O precious Lord under w[ ]",
    "Subjects": "God, prayers to; fragments; prayers, of sinners; prayers, to God",
    "Versification": "\u2014 two-line \u2014 aa",
    "_description": "A prayer to God as creator and guardian of all to help the sinful petitioner \u2014 fragments of twelve lines, possibly couplets",
    "_witnesses": {
        "BodEngMisC674": {
            "Transcription": "\nO precyous Lord vndur w[ ]All thyng dependeth b[ ]ffische fowles\n                    elementes [ ]ffor in thy diuine prescyens [ ]On the souerayne lord I\n                    synf[ ]That am thy careful creat[ ]In euery dissease thou hast b[\n                    ]And so I trust at this tyme t[ ]Seth the tyme that these Ie[\n                    ]Myn hert neuer warmed tha[ ]That was on thursday [ ]ffor of bote\n                    [ ]\n",
            "Note": "\nFragment of paper page, written in hand of the fifteenth century, found\n                    in June 1977 in Oxford,  Bodleian Library Ashmole 1518 between ff. 77 and 78; set out as verse\n                    with upper case letters at beginnings of each line.",
            "folio": "f. 1"
        }
    }
}