{
    "_id": 4359,
    "_header": "Penance is in heart reusing",
    "Subjects": "penance",
    "Versification": "\u2014 two-line \u2014 aa",
    "_description": "On Penance \u2014 six lines",
    "_witnesses": {
        "CamTCC323": {
            "First Lines": "\nPenaunce is in herte reusingein monye tellinge\u2026\n",
            "Last Lines": "\n\u2026\u00feu is god \u00feat neuer ne lei\u00deer is ioye \u00feat\n                    neuer [ ? ]\n",
            "Note": "\nTen lines (sic Person), written in 6 lines: four at bottom of\n                    col. 1 and two in the middle of col. 2, written two lines of verse per line of\n                    MS.",
            "Editions": "\nPerson,  Henry Axel. \n             Cambridge Middle English Lyrics.\n         Seattle: University of Washington Press, 1953; rev. ed. 1962: 26-7.\n",
            "folio": "f. 27v"
        }
    }
}