{
    "_id": 4383,
    "_header": "Plunged in the waw of mortal distress",
    "Author(s)": "John Lydgate (attrib.)",
    "Title(s)": "\u2018The Lamentatyon of Mary Magdaleyne\u2019",
    "Subjects": "Mary Magdalene, saint; women, as speakers/narrators",
    "Versification": "\u2014 seven-line \u2014 ababbcc",
    "_description": "\u2018The Lamentatyon of Mary Magdaleyne\u2019, ascribed incorrectly to Lydgate \u2014 102 stanzas rhyme royal, including \u2018Adiew\u2019 anaphora",
    "_witnesses": {}
}