{
    "_id": 44,
    "_header": "A for Gods will / What mean ye sirs to stand so still",
    "Note": "Ringler Jr. (1988)\nXRingler Jr., William A. Bibliography and Index of English Verse Printed 1476-1558. London: Mansell, 1988 TP 414.5",
    "Author(s)": "Henry Medwall",
    "Title(s)": "Fulgens et Lucrece",
    "Subjects": "legends",
    "Versification": "\u2014 five-line, six-line, eight-line \u2014 aabab, aabccb, aaabcccb",
    "_description": "Henry Medwall, Fulgens & Lucrece (c. A.D. 1497) \u2014 in mixed stanzas of five-, six- and eight-line stanzas",
    "_witnesses": {}
}