{
    "_id": 4410,
    "_header": "Pride wrath and envy",
    "Subjects": "sins, deadly",
    "Versification": "\u2014 two-line \u2014 aa",
    "_description": "The Seven Deadly Sins \u2014 two couplets",
    "_witnesses": {
        "CamEmm246": {
            "folio": "f. 58v"
        },
        "Salisb126": {
            "Editions": "\n\nThompson,  Sir Edward Maunde,\n                        ed.  \n             \u201cScraps from Middle English Manuscripts.\u201d \n             Englische Studien\n         1 (1877): 214-15: 214.\nBloomfield,  Morton. \n             The Seven Deadly Sins\u2026.\n         East Lansing, MI: Michigan State College Press, 1952: 208.\n\n",
            "folio": "f. 5"
        }
    }
}