{
    "_id": 4420,
    "_header": "Problems of old likeness and figures",
    "Author(s)": "John Lydgate",
    "Title(s)": "\u2018Chorle and the Birde\u2019",
    "Subjects": "birds, as narrators; fabliaux; advice, moral; envoys",
    "Versification": "\u2014 seven-line, eight-line \u2014 ababbcbc, ababbcc",
    "_description": "John Lydgate, \u2018The Chorle and the Birde\u2019 \u2014 fifty-four stanzas rhyme royal including 2-stanza envoy, plus one 8-line \u2018Verba translatoris\u2019 (ababbcbc)",
    "_witnesses": {
        "OxfBal354": {
            "First Lines": "\nProblemes of olde lyknes & fygvresWhich preved ben fructuovs of\n                    sentence\u2026\n",
            "Last Lines": "\n\u2026All thyynges ys sayd vnder correccounWith supportacion of hys\n                    benyngnyte\n",
            "Note": "\nProbably a transcript of \n            Lydgate, John, [The chorle and the birde], [Westminster: W. Caxton, 1477?] ; missing stanzas 49 and\n                    50.",
            "Attributed Title": "\n\u00dee chorle & \u00fee byrde (p. 353); Here endith \u00fee chorle\n                    & the byrde (p. 360)",
            "Facsimiles": "\n\nEarly Manuscripts at Oxford University: Facsimile\n                    of Oxford, Balliol MS 354.\n         (http://image.ox.ac.uk/show?collection=balliol&manuscript=ms354). \n",
            "folio": "pp. 353-360"
        },
        "OxfChrCh152": {
            "First Lines": "\nLerne the secound groundyd vpon scripturedesyre \u00feou neuyr in\n                    no condicoun\u2026\n",
            "Last Lines": "\n\u2026For alle ys seyde vndyr correccounWith supportacoun of your\n                    benygnyte\n",
            "Note": "\nMissing lines 274-34; f. 274 misbound, should follow f.\n                    277.",
            "Attributed Title": "\nHere endyth the tale of the Churle and hys bryd (at the end)",
            "folio": "ff. 277-291v"
        },
        "CULHh412": {
            "First Lines": "\nProblemys liknes and signesWhiche proued ben fructuose of\n                    sentence\u2026\n",
            "Last Lines": "\n\u2026all thyng is said vndyr correccionWith supportacion of\n                    \u021dowre benignite\n",
            "folio": "ff. 77v-84"
        },
        "CULKk16": {
            "First Lines": "\nProblemus lykenessus & ffygurysWhiche prued byn ffructuous of\n                    sentensse\u2026\n",
            "Last Lines": "\n\u2026In other tymes sche hath no ffantesyThus euery thyng as\n                    Clerkes spesyfye\u2026\n",
            "Note": "\nEnds imperfectly.",
            "folio": "ff. 208v-214v"
        },
        "CamTCC599": {
            "First Lines": "\n[P]roblems of olde lykenes & figuresWhyche are prouyd fructuos\n                    of sentenceAnd haue auctoryte groundyd in scriptureBy resemblance of\n                    notable apparence\u2026\n",
            "Last Lines": "\n\u2026All \u00feyng ys seyde vnder correccionWith supportacion of\n                    your benygnyte\n",
            "Attributed Title": "\nThe tale of \u00fee byrde and the Chorle of thre notable & gret wysdoms\n                    groundyd vppon these ii verses folowyng that ys to wete Ne nimis omissa\n                        doleas nec omne quod audis Credas nec optas is quod habere nequis (f.\n                        9ra)",
            "Facsimiles": "\nFletcher,  Bradford Y. \n             \u201cIntroduction.\u201d \n             Manuscript Trinity R.3.19. A Facsimile.\n         Norman, OK: Pilgrim, 1987. \n",
            "folio": "ff. 9ra-11vb"
        },
        "BlCottCalAII": {
            "First Lines": "\nPRoblemys of old lyknesse & fyguresWhyche preuyd ben fructuous\n                    of sentense\u2026\n",
            "Last Lines": "\n\u2026All thyng ys seyd vndyr correccion With supportacion of yowr\n                    benygnite\n",
            "Note": "\nTranscript by Bp. Percy, London,  British Library Addit. 39547, f. 90.\n                    \u2018Explicit\u2019 in lower margin f. 22, by scribe.",
            "Attributed Title": "\nThe Chorle (by scribe as RT, verso leaves); The chorle & \u00fee Byrd\n                    printed (added by later hand to upper margin, f. 17); Another old poeme intitled\n                    the Chorle (f. 1, sixteenth-century list of contents)",
            "folio": "ff. 17-22"
        },
        "BLHar116": {
            "First Lines": "\nPRoblemys of olde liknese and figuresWhich proued been fructuous of\n                    sentence\u2026\n",
            "Last Lines": "\n\u2026Al thing is saide vndir correctiounWith supportacion of your\n                    benignite\n",
            "Attributed Title": "\nExplicit tractatus de Aue & Carlabunde (f. 152)",
            "Editions": "\n\nHalliwell-Phillipps,  James Orchard,\n                        ed.  \n             A Selection from the Minor Poems of Don John Lydgate.\nPercy Society\n         2. London: T. Richard, 1840: 179-93.\nNeilson,  William Allan,  and  Kenneth Grant Tremaye Webster.  \n             Chief British Poets of the 14th and 15th Centuries\n         London: Dent; and New York: Dutton, 1916: 208-13.\nTyroller,  Franz. \n             \u201cDie Fabel von dem Mann und dem Vogel in ihrer Verbreitung in der\n                Weltliterature.\u201d \n             Litterarhistorische Forschungen\n         51 (Berlin, 1912): 176.\n\n",
            "folio": "fd. 146v-152"
        },
        "BLHar2407": {
            "First Lines": "\nPoyetys write wondurful lyknesand covert kepe hem selfe ful clos\u2026\n",
            "Last Lines": "\n\u2026all thyng ys sayde vnder correcciounwith supportacioun of yowre benyngnite\n",
            "Note": "\n66 stanzas. Includes envoy; incomplete pen drawings (five on ff. 76-78) to illustrate, spaces left for further drawings throughout to f. 90.",
            "Editions": "\nBowers,  Robert Hood. \n             \u201cLydgate\u2019s \u2018The Churl and the Bird\u2019 MS Harley 2407 and\n                Elias Ashmole.\u201d \n             Modern Language Notes\n         49 (1934): 90-94: 91-3 (8 stanzas only).\n",
            "folio": "ff. 76-90v"
        },
        "BLLan699": {
            "First Lines": "\nPRoblemys liknessis & ffiguresWhich previd been fructuous of\n                    sentence\u2026\n",
            "Last Lines": "\n\u2026All thyng is seide vndir correccionWith supportation of your\n                    benygnyte\n",
            "Note": "\nFolio number reflects the most recent foliation.",
            "Attributed Title": "\nIncipit de Aue & Rustico (f. 27v); Explicit Fabula\n                        de Ave & Rustico (f. 34v)",
            "Editions": "\nMacCracken,  Henry Noble,\n                        ed.  \n             John Lydgate: The Minor Poems, Vol. II: Secular Poems.\nEETS\n         o.s. 192 (1934); repr. 1961: 468-85.\n",
            "folio": "ff. 28-34v"
        },
        "Lincoln129": {
            "First Lines": "\n\u2026Mid the gardyn stood a fressh laurertheron a brid syngyng\n                    bothe day & nyhtwith sonnyssh fethers brihter than gold werwhich\n                    with hir song makith heuy hertis liht\u2026\n",
            "Last Lines": "\n\u2026all thyng is seyd vndir correcciounwith supportacioun of your\n                    benygnyte\n",
            "Note": "\nBegins imperfectly; text begins f. 68 but most of this folio torn out;\n                    can see decorated initial \u2018P\u2019 and very beginnings of lines 4-7, ends\n                    of lines on f. 68v\n",
            "Attributed Author": "\nAuth Joan. Lydgate (added by later hand, f. 74v)",
            "Attributed Title": "\nExplicit fabula de Aue & Rustico (f. 74v)",
            "Editions": "\nMacCracken,  Henry Noble,\n                        ed.  \n             John Lydgate: The Minor Poems, Vol. II: Secular Poems.\nEETS\n         o.s. 192 (1934); repr. 1961: 468-85.\n",
            "folio": "ff. 68-74v"
        },
        "Longleat258": {
            "First Lines": "\n[P]roblemes of olde likenes and figuresWhiche proued ben ful\n                    fructuous of sentence\u2026\n",
            "Last Lines": "\n\u2026Alle thing is saide vndre correciounWith supportacion of his\n                    benyngnyte\n",
            "Note": "\nLines 337-78 lost.",
            "Attributed Title": "\nHere endith the / Chorle and \u00fee bridde (f. 147)",
            "Editions": "\nHammond,  Eleanor Prescott. \n             English Verse between Chaucer and Surrey.\n         Durham, NC: Duke UP, 1927: 104-10.\n",
            "folio": "ff. 137-147"
        },
        "Austin143": {
            "First Lines": "\nNobleness of olde likenes and figuresWhich provid ben fructuous of\n                    sentens\u2026\n",
            "Last Lines": "\n\u2026And remembre you where that euere ne goneThat a Churlis Cheke\n                    [sic] is allway wo begone\u2026\n",
            "Note": "\nEnds imperfectly due to loss of leaves at l. 371; catchwords for\n                    following line: \u2018vnto the purpos\u2019.",
            "Attributed Title": "\nEt incipit / ffabula Rustici & Auis (f. 304)",
            "Editions": "\nLovell,  Robert Earl,\n                        ed.  \n             \u201cJohn Lydgate\u2019s Siege of Thebes and Churl and Bird:\n                Edited from the Cardigan-Brudenell Manuscript.\u201d \n         Diss. University of Texas at Austin, 1969: 215-34.\n",
            "folio": "ff. 304-308v"
        },
        "BosPLMed92": {
            "First Lines": "\n\u2026Sumtyme \u00feer was In a smal villargeAs myn Auctour maketh\n                    rehersayleA chorle which had lust & gret corageWith In hym self by\n                    dilligent trauayle\u2026\n",
            "Last Lines": "\n\u2026haue ofte sythe grete sorow & myschauncewho \u00feat hath\n                    fredom he hath suffisaunceBetter is fredom with lytel in\n                    gladnesse\u00dean to be thrall with all wordely rychesse\n",
            "Note": "\n48 stanzas rhyme royal; missing stanzas 1-6; MS written in Calais\n                        c. 1470 by scribe, V.C. Moris and another hand; owned by\n                    \u2018William Caston\u2019 and given by him to \u2018William Sonnyng\u2019\n                    in 1471; coat of arms of Thomas Wall on f. 1.",
            "folio": "ff. 187-189"
        },
        "HunHM144": {
            "First Lines": "\nPRoblemys of olde likenesses and figuresWhiche prouyd been\n                    fructuose of sentence\u2026\n",
            "Last Lines": "\n\u2026All thyng is sayde vnder correcciounWith supportacion of your\n                    benynghnyte\n",
            "Attributed Author": "\nLenvoy Explicit Lydgate (f. 141)",
            "Attributed Title": "\nHere begynnyth the Tale of the Chorle and the Byrde (f. 135v);\n                    Cherle & Byrde (RT)",
            "folio": "ff. 135v-144"
        },
        "Leiden": {
            "folio": "f. 42"
        }
    }
}