{
    "_id": 6121,
    "_header": "Upon a lady fair and bright",
    "Note": "Burden same as 5272.",
    "Subjects": "carols, to Virgin Mary; Virgin Mary, carols to",
    "Versification": "\u2014 five-line \u2014 ababc",
    "_description": "A song of the Virgin Mary \u2014 four five-line stanzas (ababc) including refrain, \u2018Newell\u2019 or \u2018Nowell\u2019 plus burden (cc): \u2018Newell newell newell newell / I thank a maydyn euery dele\u2019",
    "_witnesses": {
        "OxfBal354": {
            "First Lines": "\nVpon a lady fayre & brightSo hartely I haue set my\n                    thowght\u2026\n",
            "Last Lines": "\n\u2026& to Mary I mak my monefor on her I thynk & say right\n                    nowghtNowellExplicit\n",
            "Facsimiles": "\n\nEarly Manuscripts at Oxford University: Facsimile\n                    of Oxford, Balliol MS 354.\n         (http://image.ox.ac.uk/show?collection=balliol&manuscript=ms354). \n",
            "Editions": "\n\nFl\u00fcgel,  Ewald. \n             \u201cEnglische Weihnachtslieder aus einter Handschrift des Balliol College\n                zu Oxford.\u201d \n             Forschungen zur deutschen Philologie. Festgabe f\u00fcr Rudolf\n                Hildebrands.\n         Leipzig: Deit, 1894: 52-84: 54.\nFl\u00fcgel,  Ewald,\n                        ed.  \n             Neuenglisches Lesebuch.\n         1 Bd. Halle: Niemayer, 1895: 126.\nFl\u00fcgel,  Ewald. \n             \u201cLiedersammlungen des XVI Jahrhunderts\u2026.\u201d \n             Anglia\n         26 (1903): 94-285: 190.\nDyboski,  R.,\n                        ed.  \n             Songs, Carols and Other Miscellaneous Poems from Balliol MS. 354,\n                Richard Hill\u2019s Commonplace Book.\nEETS\n          e.s. 101 (1908); repr. 1984: 2.\nGreene,  Richard Leighton. \n             The Early English Carols.\n         Oxford: Clarendon, 1935; 2nd ed., rev., Oxford: Clarendon,\n            1977: 136-7; 1977, 121.\n\n",
            "folio": "p. 3742"
        }
    }
}