{
    "_id": 6149,
    "_header": "Wake man sleep not rise up and think that earth thou art",
    "Subjects": "death, approach of; mortality",
    "Versification": "\u2014 four-line, two-line \u2014 aaaa, aa",
    "_description": "Admonition to prepare for death \u2014 four long quatrains and couplet introduction; five lines interpolated",
    "_witnesses": {
        "BodLauMis733": {
            "First Lines": "\nWake man slepe not rise vp and thynk \u00feat erth thou artAnd that\n                    erth thou shal be whan the hath cayht deth smart\u2026\n",
            "Last Lines": "\n\u2026In harte he meke and contrite and than thou shall playIn Blys\n                    with hym that of a Mayde was born this day\n",
            "Note": "\nIntroductory couplet: \u2018In my bed liyng on cristis day half slepyng\n                    / Sighhis woundrous havyng A voice I hard thus spekyng.\u2019",
            "Editions": "\nBrown,  Carleton Fairchild,\n                        ed.  \n             Religious Lyrics of the XVth Century.\n         Oxford: Clarendon, 1939: 245-6.\n",
            "folio": "inner front cover"
        }
    }
}